aurora_biologic/__init__.py
aurora_biologic/biologic.py
aurora_biologic/dicts.py
aurora_biologic/mocks.py
aurora_biologic/version.py
aurora_biologic/cli/__init__.py
aurora_biologic/cli/daemon.py
aurora_biologic/cli/main.py
aurora_biologic-0.2.3.dist-info/entry_points.txt
aurora_biologic-0.2.3.dist-info/licenses/LICENSE
aurora_biologic-0.2.3.dist-info/WHEEL
aurora_biologic-0.2.3.dist-info/METADATA
aurora_biologic-0.2.3.dist-info/RECORD
