Metadata-Version: 2.4
Name: aurora-biologic
Version: 0.2.3
Summary: Python API for Biologic EC-lab potentiostats
Requires-Python: >=3.10
Classifier: Development Status :: 3 - Alpha
Classifier: License :: OSI Approved :: MIT License
Classifier: Programming Language :: Python :: 3
Classifier: Programming Language :: Python :: 3.10
Classifier: Programming Language :: Python :: 3.11
Classifier: Programming Language :: Python :: 3.12
Classifier: Programming Language :: Python :: 3.13
Classifier: Programming Language :: Python :: 3.14
Classifier: Operating System :: Microsoft :: Windows
License-File: LICENSE
Requires-Dist: comtypes>=1.4.11
Requires-Dist: platformdirs>=4.3.8
Requires-Dist: pre-commit>=4.3.0
Requires-Dist: psutil>=7.0.0
Requires-Dist: typer>=0.16.0
Requires-Dist: bumpver>=2025.1131 ; extra == "dev"
Requires-Dist: pytest>=8.4.1 ; extra == "dev"
Requires-Dist: ruff>=0.12.3 ; extra == "dev"
Provides-Extra: dev
